pangon/__init__.py
pangon/hash.py
pangon-1.0.0.dist-info/licenses/LICENSE
pangon-1.0.0.dist-info/METADATA
pangon-1.0.0.dist-info/WHEEL
pangon-1.0.0.dist-info/top_level.txt
pangon-1.0.0.dist-info/RECORD
